bs_drm_adapter/__init__.py
bs_drm_adapter/adapters.py
bs_drm_adapter/app.py
bs_drm_adapter-2.8.46.dist-info/METADATA
bs_drm_adapter-2.8.46.dist-info/WHEEL
bs_drm_adapter-2.8.46.dist-info/top_level.txt
bs_drm_adapter-2.8.46.dist-info/RECORD
