Metadata-Version: 2.1
Name: bs_drm_adapter
Version: 2.8.46
Summary: Beenius DRM Adapter
Home-page: https://git.beenius.tv/devops/tools/bs-drm-adapter
Author: Jernej Kladnik
Author-email: jernej.kladnik@beenius.tv
License: Other/Proprietary License
Project-URL: Source, https://git.beenius.tv/devops/tools/bs-drm-adapter
Project-URL: Tracker, https://git.beenius.tv/devops/tools/bs-drm-adapter/issues
Keywords: drm adapter content streaming integration
Classifier: Development Status :: 3 - Alpha
Classifier: Intended Audience :: Developers
Classifier: Intended Audience :: System Administrators
Classifier: License :: Other/Proprietary License
Classifier: Programming Language :: Python :: 3 :: Only
Classifier: Topic :: Software Development :: Libraries :: Python Modules
Requires-Python: >=3.6, <4
Requires-Dist: Flask>=1.1.2
Requires-Dist: Flask-RESTful<2.0.0,>=0.3.8
Requires-Dist: PyYAML>=5.3.1
Requires-Dist: zeep>=4.0.0
Requires-Dist: pytz>=2020.4
Requires-Dist: uWSGI>=2.0.0
